README.md
setup.py
src/canker/__init__.py
src/canker/action.py
src/canker/cli.py
src/canker/enums.py
src/canker/exceptions.py
src/canker/protocols.py
src/canker/tool.py
src/canker/util.py
src/canker/version.py
src/canker.egg-info/PKG-INFO
src/canker.egg-info/SOURCES.txt
src/canker.egg-info/dependency_links.txt
src/canker.egg-info/entry_points.txt
src/canker.egg-info/requires.txt
src/canker.egg-info/top_level.txt
src/canker/actions/__init__.py
src/canker/actions/benchmark.py
src/canker/actions/inject_flags.py
src/canker/actions/record.py
test/test_action.py
test/test_enums.py
test/test_tool.py
test/test_util.py