Metadata-Version: 2.1
Name: canker
Version: 0.0.10
Summary: A catch-all compile-tool wrapper
Home-page: https://github.com/trailofbits/canker
Author: William Woodruff
Author-email: william@trailofbits.com
License: Apache-2.0
Project-URL: Documentation, https://trailofbits.github.io/canker/
Platform: any
Requires-Python: >=3.7
Provides-Extra: dev
